actions_in_fly/__init__.py
actions_in_fly/__main__.py
actions_in_fly/fly.py
actions_in_fly-0.2.1.dist-info/entry_points.txt
actions_in_fly-0.2.1.dist-info/WHEEL
actions_in_fly-0.2.1.dist-info/METADATA
actions_in_fly-0.2.1.dist-info/RECORD
